uchida1512testpackage/__init__.py
uchida1512testpackage-1.0.0.dist-info/LICENSE.txt
uchida1512testpackage-1.0.0.dist-info/METADATA
uchida1512testpackage-1.0.0.dist-info/WHEEL
uchida1512testpackage-1.0.0.dist-info/top_level.txt
uchida1512testpackage-1.0.0.dist-info/RECORD
